{
  "name": "home",
  "title": "Home",
  "components": [
    {
      "id": "container-1",
      "type": "Container",
      "props": {
        "maxWidth": "1200px"
      },
      "style": {
        "padding": "40px 20px"
      },
      "children": [
        {
          "id": "heading-1",
          "type": "Heading",
          "props": {
            "level": 1,
            "text": "Welcome to the Dynamic CMS"
          },
          "style": {
            "textAlign": "center",
            "marginBottom": "20px"
          },
          "children": []
        },
        {
          "id": "text-1",
          "type": "Text",
          "props": {
            "content": "This is a dynamic content management system powered by React and GitHub. You can create, edit, and manage your content through an intuitive interface."
          },
          "style": {
            "textAlign": "center",
            "marginBottom": "40px",
            "fontSize": "18px"
          },
          "children": []
        }
      ]
    }
  ]
}
